[
  {
    "id": "1",
    "nombre": "Luchi",
    "email": "a@a.com",
    "contrasenia": "$2a$10$xtR2k7RHLCDBMnuNc5ZiheqRqxwF/Vg5Mxt3HYAt0T/q4ZAdEwB9e",
    "delete": false
  },
  {
    "id": "11",
    "nombre": "Shaine Sara",
    "email": "sheine.siro@gmail.com",
    "contrasenia": "$2a$10$ZdSqMOhq8/hv0GFtCOidOuynYpQ9OVP0IWl2rwjeAAnMdjZELb.hC",
    "roles": "administrador",
    "delete": false,
    "imgs": {
      "id": 1,
      "img": "/img/products/lecheDeAlmendraYcoco.jpg",
      "alt": "Leche de almendras y coco"
    }
  },
  {
    "id": "111",
    "nombre": "sdds",
    "email": "jorgemartindominguezdiaz@gmail.com",
    "contrasenia": "jorge123",
    "confirmarContrasenia": "jorge123",
    "imgs": {},
    "delete": false
  },
  {
    "id": "1111",
    "nombre": "ddss",
    "email": "jorgenick69@gmail.com",
    "contrasenia": "jorge123",
    "confirmarContrasenia": "jorge123",
    "imgs": [
      {
        "id": 1,
        "img": "/img/users/user-cebada_1675384501724.webp",
        "alt": "cebada.webp"
      }
    ],
    "delete": false
  }
]